gpuwidget/__init__.py
gpuwidget/core.py
gpuwidget/widgets.py
gpuwidget-0.1.2.dist-info/LICENSE
gpuwidget-0.1.2.dist-info/METADATA
gpuwidget-0.1.2.dist-info/WHEEL
gpuwidget-0.1.2.dist-info/top_level.txt
gpuwidget-0.1.2.dist-info/RECORD
