Metadata-Version: 2.1
Name: gpuwidget
Version: 0.1.2
Summary: A Jupyter widget for monitoring NVIDIA GPUs.
Author-email: Wenbo Pan <pixelwenbo@gmail.com>
License: Creative Commons Legal Code
Project-URL: homepage, https://github.com/bmpixel/gpuwidget
Project-URL: repository, https://github.com/bmpixel/gpuwidget
Project-URL: documentation, https://github.com/bmpixel/gpuwidget#readme
Keywords: jupyter,gpu,monitoring,widget,nvidia
Classifier: Development Status :: 3 - Alpha
Classifier: Intended Audience :: Developers
Classifier: License :: CC0 1.0 Universal (CC0 1.0) Public Domain Dedication
Classifier: Operating System :: OS Independent
Classifier: Programming Language :: Python :: 3
Classifier: Programming Language :: Python :: 3.6
Classifier: Programming Language :: Python :: 3.7
Classifier: Programming Language :: Python :: 3.8
Classifier: Programming Language :: Python :: 3.9
Classifier: Programming Language :: Python :: 3.10
Classifier: Programming Language :: Python :: 3.11
Classifier: Topic :: Software Development :: Libraries :: Python Modules
Classifier: Framework :: Jupyter
License-File: LICENSE
Requires-Dist: ipywidgets >=7.6
Requires-Dist: gpustat >=1.0
